Workbook
Name Slicer_Department1: #N/A

Sheet Employee Master Dataset
A1: Employee ID | B1: Name | C1: Department | D1: Title | E1: Recruitment Date | F1: Performance Manager | G1: Unit / Location | H1: Country | I1: Employment Type | J1: Job Level | K1: Job Grade | L1: Monthly Gross Salary | M1: Pay Frequency | N1: Min | O1: Mid | P1: Max | Q1: Compa_Ratio (GrossSalary/Mid) | R1: Compa-Ratio Group | S1: Performance | T1: Salary increase % | U1: Salary increase Amount | V1: New Gross Salary | W1: STI % | X1: Target STI | Y1: Multiplier | Z1: Final STI | AA1: Tax % | AB1: Benefit Plan | AC1: Tax Amount (New Gross Salary + Final STI)*Tax %) | AD1: Pension (New Gross Salary*5%) | AE1: Health Premium (A/B/C) | AF1: Total Deductions (Tax+Pension+HP) | AG1: Net Pay (New Gross Salary+Final STI-Total Deductions)
A2: 1001 | B2: Employee 1 | C2: IT | D2: IT Specialist | E2: 44927 | F2: Manager 1 | G2: Malmö | H2: Sweden | I2: Full time | J2: Level 2 | K2: G5 | L2: 34245 | M2: Monthly | N2: 30000 | O2: 35000 | P2: 40000 | Q2: =Table13[[#This Row],[Monthly Gross Salary]]/Table13[[#This Row],[Mid]] -> 0.97842857 | R2: =IF(Q2<0.85,"Very Low", IF(Q2<0.95,"Below Mid", IF(Q2<=1.05,"Around Mid", IF(Q2<=1.15,"Above Mid","High")))) -> Around Mid | S2: 4 | T2: =INDEX('Merit Matrix'!$B$4:$F$8, MATCH($S2,'Merit Matrix'!$A$4:$A$8,0), MATCH(TRIM($R2),'Merit Matrix'!$B$3:$F$3,0)) -> 0.04 | U2: =Table13[[#This Row],[Salary increase %]]*Table13[[#This Row],[Monthly Gross Salary]] -> 1369.8 | V2: =Table13[[#This Row],[Salary increase Amount]]+Table13[[#This Row],[Monthly Gross Salary]] -> 35614.8 | W2: 0.1 | X2: =Table13[[#This Row],[New Gross Salary]]*Table13[[#This Row],[STI %]] -> 3561.48 | Y2: 1.2 | Z2: =Table13[[#This Row],[Target STI]]*Table13[[#This Row],[Multiplier]] -> 4273.776 | AA2: 0.29 | AB2: C | AC2: =(Table13[[#This Row],[New Gross Salary]]+Table13[[#This Row],[Final STI]])*Table13[[#This Row],[Tax %]] -> 11567.687 | AD2: =Table13[[#This Row],[New Gross Salary]]*5% -> 1780.74 | AE2: {=_xlfn.XLOOKUP(AB2,{"A","B","C"},{500,800,1200})} -> 1200 | AF2: =SUM(AC2:AE2) -> 14548.427 | AG2: =Table13[[#This Row],[New Gross Salary]]+Table13[[#This Row],[Final STI]]-Table13[[#This Row],[Total Deductions (Tax+Pension+HP)]] -> 25340.149
A3: 1002 | B3: Employee 2 | C3: HR | D3: HR Specialist | E3: 45292 | F3: Manager 2 | G3: Stockholm | H3: Sweden | I3: Full time | J3: Level 2 | K3: G6 | L3: 41804 | M3: Monthly | N3: 35000 | O3: 40000 | P3: 45000 | Q3: =Table13[[#This Row],[Monthly Gross Salary]]/Table13[[#This Row],[Mid]] -> 1.0451 | R3: =IF(Q3<0.85,"Very Low", IF(Q3<0.95,"Below Mid", IF(Q3<=1.05,"Around Mid", IF(Q3<=1.15,"Above Mid","High")))) -> Around Mid | S3: 3 | T3: =INDEX('Merit Matrix'!$B$4:$F$8, MATCH($S3,'Merit Matrix'!$A$4:$A$8,0), MATCH(TRIM($R3),'Merit Matrix'!$B$3:$F$3,0)) -> 0.025 | U3: =Table13[[#This Row],[Salary increase %]]*Table13[[#This Row],[Monthly Gross Salary]] -> 1045.1 | V3: =Table13[[#This Row],[Salary increase Amount]]+Table13[[#This Row],[Monthly Gross Salary]] -> 42849.1 | W3: 0.1 | X3: =Table13[[#This Row],[New Gross Salary]]*Table13[[#This Row],[STI %]] -> 4284.91 | Y3: 1 | Z3: =Table13[[#This Row],[Target STI]]*Table13[[#This Row],[Multiplier]] -> 4284.91 | AA3: 0.27 | AB3: B | AC3: =(Table13[[#This Row],[New Gross Salary]]+Table13[[#This Row],[Final STI]])*Table13[[#This Row],[Tax %]] -> 12726.183 | AD3: =Table13[[#This Row],[New Gross Salary]]*5% -> 2142.455 | AE3: {=_xlfn.XLOOKUP(AB3,{"A","B","C"},{500,800,1200})} -> 800 | AF3: =SUM(AC3:AE3) -> 15668.638 | AG3: =Table13[[#This Row],[New Gross Salary]]+Table13[[#This Row],[Final STI]]-Table13[[#This Row],[Total Deductions (Tax+Pension+HP)]] -> 31465.372
A4: 1003 | B4: Employee 3 | C4: Finance | D4: Finance Specialist | E4: 45292 | F4: Manager 3 | G4: Göteborg | H4: Sweden | I4: Full time | J4: Level 2 | K4: G5 | L4: 34245 | M4: Monthly | N4: 30000 | O4: 35000 | P4: 40000 | Q4: =Table13[[#This Row],[Monthly Gross Salary]]/Table13[[#This Row],[Mid]] -> 0.97842857 | R4: =IF(Q4<0.85,"Very Low", IF(Q4<0.95,"Below Mid", IF(Q4<=1.05,"Around Mid", IF(Q4<=1.15,"Above Mid","High")))) -> Around Mid | S4: 3 | T4: =INDEX('Merit Matrix'!$B$4:$F$8, MATCH($S4,'Merit Matrix'!$A$4:$A$8,0), MATCH(TRIM($R4),'Merit Matrix'!$B$3:$F$3,0)) -> 0.025 | U4: =Table13[[#This Row],[Salary increase %]]*Table13[[#This Row],[Monthly Gross Salary]] -> 856.125 | V4: =Table13[[#This Row],[Salary increase Amount]]+Table13[[#This Row],[Monthly Gross Salary]] -> 35101.125 | W4: 0.1 | X4: =Table13[[#This Row],[New Gross Salary]]*Table13[[#This Row],[STI %]] -> 3510.1125 | Y4: 1 | Z4: =Table13[[#This Row],[Target STI]]*Table13[[#This Row],[Multiplier]] -> 3510.1125 | AA4: 0.31 | AB4: B | AC4: =(Table13[[#This Row],[New Gross Salary]]+Table13[[#This Row],[Final STI]])*Table13[[#This Row],[Tax %]] -> 11969.484 | AD4: =Table13[[#This Row],[New Gross Salary]]*5% -> 1755.0563 | AE4: {=_xlfn.XLOOKUP(AB4,{"A","B","C"},{500,800,1200})} -> 800 | AF4: =SUM(AC4:AE4) -> 14524.54 | AG4: =Table13[[#This Row],[New Gross Salary]]+Table13[[#This Row],[Final STI]]-Table13[[#This Row],[Total Deductions (Tax+Pension+HP)]] -> 24086.698
A5: 1004 | B5: Employee 4 | C5: IT | D5: IT Specialist | E5: 44927 | F5: Manager 4 | G5: Linköping | H5: Sweden | I5: Full time | J5: Level 2 | K5: G5 | L5: 34245 | M5: Monthly | N5: 30000 | O5: 35000 | P5: 40000 | Q5: =Table13[[#This Row],[Monthly Gross Salary]]/Table13[[#This Row],[Mid]] -> 0.97842857 | R5: =IF(Q5<0.85,"Very Low", IF(Q5<0.95,"Below Mid", IF(Q5<=1.05,"Around Mid", IF(Q5<=1.15,"Above Mid","High")))) -> Around Mid | S5: 4 | T5: =INDEX('Merit Matrix'!$B$4:$F$8, MATCH($S5,'Merit Matrix'!$A$4:$A$8,0), MATCH(TRIM($R5),'Merit Matrix'!$B$3:$F$3,0)) -> 0.04 | U5: =Table13[[#This Row],[Salary increase %]]*Table13[[#This Row],[Monthly Gross Salary]] -> 1369.8 | V5: =Table13[[#This Row],[Salary increase Amount]]+Table13[[#This Row],[Monthly Gross Salary]] -> 35614.8 | W5: 0.1 | X5: =Table13[[#This Row],[New Gross Salary]]*Table13[[#This Row],[STI %]] -> 3561.48 | Y5: 1.2 | Z5: =Table13[[#This Row],[Target STI]]*Table13[[#This Row],[Multiplier]] -> 4273.776 | AA5: 0.28 | AB5: B | AC5: =(Table13[[#This Row],[New Gross Salary]]+Table13[[#This Row],[Final STI]])*Table13[[#This Row],[Tax %]] -> 11168.801 | AD5: =Table13[[#This Row],[New Gross Salary]]*5% -> 1780.74 | AE5: {=_xlfn.XLOOKUP(AB5,{"A","B","C"},{500,800,1200})} -> 800 | AF5: =SUM(AC5:AE5) -> 13749.541 | AG5: =Table13[[#This Row],[New Gross Salary]]+Table13[[#This Row],[Final STI]]-Table13[[#This Row],[Total Deductions (Tax+Pension+HP)]] -> 26139.035
A6: 1005 | B6: Employee 5 | C6: Marketing | D6: Marketing Specialist | E6: 44927 | F6: Manager 5 | G6: Örebro | H6: Sweden | I6: Full time | J6: Level 2 | K6: G5 | L6: 34245 | M6: Monthly | N6: 30000 | O6: 35000 | P6: 40000 | Q6: =Table13[[#This Row],[Monthly Gross Salary]]/Table13[[#This Row],[Mid]] -> 0.97842857 | R6: =IF(Q6<0.85,"Very Low", IF(Q6<0.95,"Below Mid", IF(Q6<=1.05,"Around Mid", IF(Q6<=1.15,"Above Mid","High")))) -> Around Mid | S6: 5 | T6: =INDEX('Merit Matrix'!$B$4:$F$8, MATCH($S6,'Merit Matrix'!$A$4:$A$8,0), MATCH(TRIM($R6),'Merit Matrix'!$B$3:$F$3,0)) -> 0.06 | U6: =Table13[[#This Row],[Salary increase %]]*Table13[[#This Row],[Monthly Gross Salary]] -> 2054.7 | V6: =Table13[[#This Row],[Salary increase Amount]]+Table13[[#This Row],[Monthly Gross Salary]] -> 36299.7 | W6: 0.1 | X6: =Table13[[#This Row],[New Gross Salary]]*Table13[[#This Row],[STI %]] -> 3629.97 | Y6: 1.5 | Z6: =Table13[[#This Row],[Target STI]]*Table13[[#This Row],[Multiplier]] -> 5444.955 | AA6: 0.32 | AB6: C | AC6: =(Table13[[#This Row],[New Gross Salary]]+Table13[[#This Row],[Final STI]])*Table13[[#This Row],[Tax %]] -> 13358.29 | AD6: =Table13[[#This Row],[New Gross Salary]]*5% -> 1814.985 | AE6: {=_xlfn.XLOOKUP(AB6,{"A","B","C"},{500,800,1200})} -> 1200 | AF6: =SUM(AC6:AE6) -> 16373.275 | AG6: =Table13[[#This Row],[New Gross Salary]]+Table13[[#This Row],[Final STI]]-Table13[[#This Row],[Total Deductions (Tax+Pension+HP)]] -> 25371.38
A7: 1006 | B7: Employee 6 | C7: Marketing | D7: Marketing Specialist | E7: 44927 | F7: Manager 6 | G7: Stockholm | H7: Sweden | I7: Full time | J7: Level 2 | K7: G5 | L7: 34245 | M7: Monthly | N7: 30000 | O7: 35000 | P7: 40000 | Q7: =Table13[[#This Row],[Monthly Gross Salary]]/Table13[[#This Row],[Mid]] -> 0.97842857 | R7: =IF(Q7<0.85,"Very Low", IF(Q7<0.95,"Below Mid", IF(Q7<=1.05,"Around Mid", IF(Q7<=1.15,"Above Mid","High")))) -> Around Mid | S7: 5 | T7: =INDEX('Merit Matrix'!$B$4:$F$8, MATCH($S7,'Merit Matrix'!$A$4:$A$8,0), MATCH(TRIM($R7),'Merit Matrix'!$B$3:$F$3,0)) -> 0.06 | U7: =Table13[[#This Row],[Salary increase %]]*Table13[[#This Row],[Monthly Gross Salary]] -> 2054.7 | V7: =Table13[[#This Row],[Salary increase Amount]]+Table13[[#This Row],[Monthly Gross Salary]] -> 36299.7 | W7: 0.1 | X7: =Table13[[#This Row],[New Gross Salary]]*Table13[[#This Row],[STI %]] -> 3629.97 | Y7: 1.5 | Z7: =Table13[[#This Row],[Target STI]]*Table13[[#This Row],[Multiplier]] -> 5444.955 | AA7: 0.28 | AB7: C | AC7: =(Table13[[#This Row],[New Gross Salary]]+Table13[[#This Row],[Final STI]])*Table13[[#This Row],[Tax %]] -> 11688.503 | AD7: =Table13[[#This Row],[New Gross Salary]]*5% -> 1814.985 | AE7: {=_xlfn.XLOOKUP(AB7,{"A","B","C"},{500,800,1200})} -> 1200 | AF7: =SUM(AC7:AE7) -> 14703.488 | AG7: =Table13[[#This Row],[New Gross Salary]]+Table13[[#This Row],[Final STI]]-Table13[[#This Row],[Total Deductions (Tax+Pension+HP)]] -> 27041.167
A8: 1007 | B8: Employee 7 | C8: Sales | D8: Sales Specialist | E8: 45292 | F8: Manager 7 | G8: Göteborg | H8: Sweden | I8: Full time | J8: Level 2 | K8: G5 | L8: 34245 | M8: Monthly | N8: 30000 | O8: 35000 | P8: 40000 | Q8: =Table13[[#This Row],[Monthly Gross Salary]]/Table13[[#This Row],[Mid]] -> 0.97842857 | R8: =IF(Q8<0.85,"Very Low", IF(Q8<0.95,"Below Mid", IF(Q8<=1.05,"Around Mid", IF(Q8<=1.15,"Above Mid","High")))) -> Around Mid | S8: 5 | T8: =INDEX('Merit Matrix'!$B$4:$F$8, MATCH($S8,'Merit Matrix'!$A$4:$A$8,0), MATCH(TRIM($R8),'Merit Matrix'!$B$3:$F$3,0)) -> 0.06 | U8: =Table13[[#This Row],[Salary increase %]]*Table13[[#This Row],[Monthly Gross Salary]] -> 2054.7 | V8: =Table13[[#This Row],[Salary increase Amount]]+Table13[[#This Row],[Monthly Gross Salary]] -> 36299.7 | W8: 0.1 | X8: =Table13[[#This Row],[New Gross Salary]]*Table13[[#This Row],[STI %]] -> 3629.97 | Y8: 1.5 | Z8: =Table13[[#This Row],[Target STI]]*Table13[[#This Row],[Multiplier]] -> 5444.955 | AA8: 0.29 | AB8: A | AC8: =(Table13[[#This Row],[New Gross Salary]]+Table13[[#This Row],[Final STI]])*Table13[[#This Row],[Tax %]] -> 12105.95 | AD8: =Table13[[#This Row],[New Gross Salary]]*5% -> 1814.985 | AE8: {=_xlfn.XLOOKUP(AB8,{"A","B","C"},{500,800,1200})} -> 500 | AF8: =SUM(AC8:AE8) -> 14420.935 | AG8: =Table13[[#This Row],[New Gross Salary]]+Table13[[#This Row],[Final STI]]-Table13[[#This Row],[Total Deductions (Tax+Pension+HP)]] -> 27323.72
A9: 1008 | B9: Employee 8 | C9: IT | D9: IT Specialist | E9: 44927 | F9: Manager 8 | G9: Stockholm | H9: Sweden | I9: Full time | J9: Level 2 | K9: G5 | L9: 34245 | M9: Monthly | N9: 30000 | O9: 35000 | P9: 40000 | Q9: =Table13[[#This Row],[Monthly Gross Salary]]/Table13[[#This Row],[Mid]] -> 0.97842857 | R9: =IF(Q9<0.85,"Very Low", IF(Q9<0.95,"Below Mid", IF(Q9<=1.05,"Around Mid", IF(Q9<=1.15,"Above Mid","High")))) -> Around Mid | S9: 5 | T9: =INDEX('Merit Matrix'!$B$4:$F$8, MATCH($S9,'Merit Matrix'!$A$4:$A$8,0), MATCH(TRIM($R9),'Merit Matrix'!$B$3:$F$3,0)) -> 0.06 | U9: =Table13[[#This Row],[Salary increase %]]*Table13[[#This Row],[Monthly Gross Salary]] -> 2054.7 | V9: =Table13[[#This Row],[Salary increase Amount]]+Table13[[#This Row],[Monthly Gross Salary]] -> 36299.7 | W9: 0.1 | X9: =Table13[[#This Row],[New Gross Salary]]*Table13[[#This Row],[STI %]] -> 3629.97 | Y9: 1.5 | Z9: =Table13[[#This Row],[Target STI]]*Table13[[#This Row],[Multiplier]] -> 5444.955 | AA9: 0.3 | AB9: C | AC9: =(Table13[[#This Row],[New Gross Salary]]+Table13[[#This Row],[Final STI]])*Table13[[#This Row],[Tax %]] -> 12523.396 | AD9: =Table13[[#This Row],[New Gross Salary]]*5% -> 1814.985 | AE9: {=_xlfn.XLOOKUP(AB9,{"A","B","C"},{500,800,1200})} -> 1200 | AF9: =SUM(AC9:AE9) -> 15538.381 | AG9: =Table13[[#This Row],[New Gross Salary]]+Table13[[#This Row],[Final STI]]-Table13[[#This Row],[Total Deductions (Tax+Pension+HP)]] -> 26206.273
A10: 1009 | B10: Employee 9 | C10: Sales | D10: Sales Specialist | E10: 45292 | F10: Manager 9 | G10: Göteborg | H10: Sweden | I10: Full time | J10: Level 2 | K10: G5 | L10: 34245 | M10: Monthly | N10: 30000 | O10: 35000 | P10: 40000 | Q10: =Table13[[#This Row],[Monthly Gross Salary]]/Table13[[#This Row],[Mid]] -> 0.97842857 | R10: =IF(Q10<0.85,"Very Low", IF(Q10<0.95,"Below Mid", IF(Q10<=1.05,"Around Mid", IF(Q10<=1.15,"Above Mid","High")))) -> Around Mid | S10: 5 | T10: =INDEX('Merit Matrix'!$B$4:$F$8, MATCH($S10,'Merit Matrix'!$A$4:$A$8,0), MATCH(TRIM($R10),'Merit Matrix'!$B$3:$F$3,0)) -> 0.06 | U10: =Table13[[#This Row],[Salary increase %]]*Table13[[#This Row],[Monthly Gross Salary]] -> 2054.7 | V10: =Table13[[#This Row],[Salary increase Amount]]+Table13[[#This Row],[Monthly Gross Salary]] -> 36299.7 | W10: 0.1 | X10: =Table13[[#This Row],[New Gross Salary]]*Table13[[#This Row],[STI %]] -> 3629.97 | Y10: 1.5 | Z10: =Table13[[#This Row],[Target STI]]*Table13[[#This Row],[Multiplier]] -> 5444.955 | AA10: 0.32 | AB10: C | AC10: =(Table13[[#This Row],[New Gross Salary]]+Table13[[#This Row],[Final STI]])*Table13[[#This Row],[Tax %]] -> 13358.29 | AD10: =Table13[[#This Row],[New Gross Salary]]*5% -> 1814.985 | AE10: {=_xlfn.XLOOKUP(AB10,{"A","B","C"},{500,800,1200})} -> 1200 | AF10: =SUM(AC10:AE10) -> 16373.275 | AG10: =Table13[[#This Row],[New Gross Salary]]+Table13[[#This Row],[Final STI]]-Table13[[#This Row],[Total Deductions (Tax+Pension+HP)]] -> 25371.38
A11: 1010 | B11: Employee 10 | C11: Finance | D11: Finance Specialist | E11: 45292 | F11: Manager 10 | G11: Stockholm | H11: Sweden | I11: Full time | J11: Level 2 | K11: G5 | L11: 34245 | M11: Monthly | N11: 30000 | O11: 35000 | P11: 40000 | Q11: =Table13[[#This Row],[Monthly Gross Salary]]/Table13[[#This Row],[Mid]] -> 0.97842857 | R11: =IF(Q11<0.85,"Very Low", IF(Q11<0.95,"Below Mid", IF(Q11<=1.05,"Around Mid", IF(Q11<=1.15,"Above Mid","High")))) -> Around Mid | S11: 5 | T11: =INDEX('Merit Matrix'!$B$4:$F$8, MATCH($S11,'Merit Matrix'!$A$4:$A$8,0), MATCH(TRIM($R11),'Merit Matrix'!$B$3:$F$3,0)) -> 0.06 | U11: =Table13[[#This Row],[Salary increase %]]*Table13[[#This Row],[Monthly Gross Salary]] -> 2054.7 | V11: =Table13[[#This Row],[Salary increase Amount]]+Table13[[#This Row],[Monthly Gross Salary]] -> 36299.7 | W11: 0.1 | X11: =Table13[[#This Row],[New Gross Salary]]*Table13[[#This Row],[STI %]] -> 3629.97 | Y11: 1.5 | Z11: =Table13[[#This Row],[Target STI]]*Table13[[#This Row],[Multiplier]] -> 5444.955 | AA11: 0.32 | AB11: A | AC11: =(Table13[[#This Row],[New Gross Salary]]+Table13[[#This Row],[Final STI]])*Table13[[#This Row],[Tax %]] -> 13358.29 | AD11: =Table13[[#This Row],[New Gross Salary]]*5% -> 1814.985 | AE11: {=_xlfn.XLOOKUP(AB11,{"A","B","C"},{500,800,1200})} -> 500 | AF11: =SUM(AC11:AE11) -> 15673.275 | AG11: =Table13[[#This Row],[New Gross Salary]]+Table13[[#This Row],[Final STI]]-Table13[[#This Row],[Total Deductions (Tax+Pension+HP)]] -> 26071.38
A12: 1011 | B12: Employee 11 | C12: IT | D12: IT Specialist | E12: 44927 | F12: Manager 11 | G12: Stockholm | H12: Sweden | I12: Full time | J12: Level 2 | K12: G5 | L12: 34245 | M12: Monthly | N12: 30000 | O12: 35000 | P12: 40000 | Q12: =Table13[[#This Row],[Monthly Gross Salary]]/Table13[[#This Row],[Mid]] -> 0.97842857 | R12: =IF(Q12<0.85,"Very Low", IF(Q12<0.95,"Below Mid", IF(Q12<=1.05,"Around Mid", IF(Q12<=1.15,"Above Mid","High")))) -> Around Mid | S12: 5 | T12: =INDEX('Merit Matrix'!$B$4:$F$8, MATCH($S12,'Merit Matrix'!$A$4:$A$8,0), MATCH(TRIM($R12),'Merit Matrix'!$B$3:$F$3,0)) -> 0.06 | U12: =Table13[[#This Row],[Salary increase %]]*Table13[[#This Row],[Monthly Gross Salary]] -> 2054.7 | V12: =Table13[[#This Row],[Salary increase Amount]]+Table13[[#This Row],[Monthly Gross Salary]] -> 36299.7 | W12: 0.1 | X12: =Table13[[#This Row],[New Gross Salary]]*Table13[[#This Row],[STI %]] -> 3629.97 | Y12: 1.5 | Z12: =Table13[[#This Row],[Target STI]]*Table13[[#This Row],[Multiplier]] -> 5444.955 | AA12: 0.3 | AB12: A | AC12: =(Table13[[#This Row],[New Gross Salary]]+Table13[[#This Row],[Final STI]])*Table13[[#This Row],[Tax %]] -> 12523.396 | AD12: =Table13[[#This Row],[New Gross Salary]]*5% -> 1814.985 | AE12: {=_xlfn.XLOOKUP(AB12,{"A","B","C"},{500,800,1200})} -> 500 | AF12: =SUM(AC12:AE12) -> 14838.381 | AG12: =Table13[[#This Row],[New Gross Salary]]+Table13[[#This Row],[Final STI]]-Table13[[#This Row],[Total Deductions (Tax+Pension+HP)]] -> 26906.273
A13: 1012 | B13: Employee 12 | C13: IT | D13: IT Specialist | E13: 44927 | F13: Manager 12 | G13: Stockholm | H13: Sweden | I13: Full time | J13: Level 2 | K13: G5 | L13: 34245 | M13: Monthly | N13: 30000 | O13: 35000 | P13: 40000 | Q13: =Table13[[#This Row],[Monthly Gross Salary]]/Table13[[#This Row],[Mid]] -> 0.97842857 | R13: =IF(Q13<0.85,"Very Low", IF(Q13<0.95,"Below Mid", IF(Q13<=1.05,"Around Mid", IF(Q13<=1.15,"Above Mid","High")))) -> Around Mid | S13: 5 | T13: =INDEX('Merit Matrix'!$B$4:$F$8, MATCH($S13,'Merit Matrix'!$A$4:$A$8,0), MATCH(TRIM($R13),'Merit Matrix'!$B$3:$F$3,0)) -> 0.06 | U13: =Table13[[#This Row],[Salary increase %]]*Table13[[#This Row],[Monthly Gross Salary]] -> 2054.7 | V13: =Table13[[#This Row],[Salary increase Amount]]+Table13[[#This Row],[Monthly Gross Salary]] -> 36299.7 | W13: 0.1 | X13: =Table13[[#This Row],[New Gross Salary]]*Table13[[#This Row],[STI %]] -> 3629.97 | Y13: 1.5 | Z13: =Table13[[#This Row],[Target STI]]*Table13[[#This Row],[Multiplier]] -> 5444.955 | AA13: 0.3 | AB13: C | AC13: =(Table13[[#This Row],[New Gross Salary]]+Table13[[#This Row],[Final STI]])*Table13[[#This Row],[Tax %]] -> 12523.396 | AD13: =Table13[[#This Row],[New Gross Salary]]*5% -> 1814.985 | AE13: {=_xlfn.XLOOKUP(AB13,{"A","B","C"},{500,800,1200})} -> 1200 | AF13: =SUM(AC13:AE13) -> 15538.381 | AG13: =Table13[[#This Row],[New Gross Salary]]+Table13[[#This Row],[Final STI]]-Table13[[#This Row],[Total Deductions (Tax+Pension+HP)]] -> 26206.273
... A251: 1250 | B251: Employee 250 | C251: IT | D251: Head of IT | E251: 43101 | F251: CEO | G251: Umeå | H251: Sweden | I251: Full time | J251: Level 8 | K251: G10 | L251: 95656 | M251: Monthly | N251: 66959 | O251: 95656 | P251: 124353 | Q251: =Table13[[#This Row],[Monthly Gross Salary]]/Table13[[#This Row],[Mid]] -> 1 | R251: =IF(Q251<0.85,"Very Low", IF(Q251<0.95,"Below Mid", IF(Q251<=1.05,"Around Mid", IF(Q251<=1.15,"Above Mid","High")))) -> Around Mid | S251: 5 | T251: =INDEX('Merit Matrix'!$B$4:$F$8, MATCH($S251,'Merit Matrix'!$A$4:$A$8,0), MATCH(TRIM($R251),'Merit Matrix'!$B$3:$F$3,0)) -> 0.06 | U251: =Table13[[#This Row],[Salary increase %]]*Table13[[#This Row],[Monthly Gross Salary]] -> 5739.36 | V251: =Table13[[#This Row],[Salary increase Amount]]+Table13[[#This Row],[Monthly Gross Salary]] -> 101395.36 | W251: 0.25 | X251: =Table13[[#This Row],[New Gross Salary]]*Table13[[#This Row],[STI %]] -> 25348.84 | Y251: 1.5 | Z251: =Table13[[#This Row],[Target STI]]*Table13[[#This Row],[Multiplier]] -> 38023.26 | AA251: 0.32 | AB251: A | AC251: =(Table13[[#This Row],[New Gross Salary]]+Table13[[#This Row],[Final STI]])*Table13[[#This Row],[Tax %]] -> 44613.958 | AD251: =Table13[[#This Row],[New Gross Salary]]*5% -> 5069.768 | AE251: {=_xlfn.XLOOKUP(AB251,{"A","B","C"},{500,800,1200})} -> 500 | AF251: =SUM(AC251:AE251) -> 50183.726 | AG251: =Table13[[#This Row],[New Gross Salary]]+Table13[[#This Row],[Final STI]]-Table13[[#This Row],[Total Deductions (Tax+Pension+HP)]] -> 89234.894

Sheet Merit Increase Impact (2026)
A2: Unit / Location | B2: (All)
A4: Row Labels | B4: Number of Employee | C4: Average Gross Salary (2025) | D4: Average Gross Salary (2026) | E4: Sum of Gross Salary (2025) | F4: Sum of Gross Salary (2026) | G4: Sum of % Budget Increase
A5: Finance | B5: 42 | C5: 53452.81 | D5: 54695.355 | E5: 2245018 | F5: 2297204.9 | G5: 0.023245658
A6: 1 | B6: 1 | C6: 39911 | D6: 39911 | E6: 39911 | F6: 39911 | G6: 0
A7: 2 | B7: 8 | C7: 43500 | D7: 44205 | E7: 348000 | F7: 353640 | G7: 0.016206897
A8: 3 | B8: 24 | C8: 54158.583 | D8: 55360.837 | E8: 1299806 | F8: 1328660.1 | G8: 0.022198767
A9: 4 | B9: 6 | C9: 65525.833 | D9: 66833.178 | E9: 393155 | F9: 400999.07 | G9: 0.019951597
A10: 5 | B10: 3 | C10: 54715.333 | D10: 57998.253 | E10: 164146 | F10: 173994.76 | G10: 0.06
A11: HR | B11: 35 | C11: 53253.314 | D11: 54742.334 | E11: 1863866 | F11: 1915981.7 | G11: 0.027961071
A12: 2 | B12: 4 | C12: 43500 | D12: 44205 | E12: 174000 | F12: 176820 | G12: 0.016206897
A13: 3 | B13: 27 | C13: 54207.481 | D13: 55547.846 | E13: 1463602 | F13: 1499791.9 | G13: 0.024726565
A14: 4 | B14: 1 | C14: 47000 | D14: 49350 | E14: 47000 | F14: 49350 | G14: 0.05
A15: 5 | B15: 3 | C15: 59754.667 | D15: 63339.947 | E15: 179264 | F15: 190019.84 | G15: 0.06
A16: IT | B16: 51 | C16: 65219.176 | D16: 66478.89 | E16: 3326178 | F16: 3390423.4 | G16: 0.019315082
A17: 2 | B17: 5 | C17: 88313 | D17: 88313 | E17: 441565 | F17: 441565 | G17: 0
A18: 3 | B18: 30 | C18: 64692.733 | D18: 65838.416 | E18: 1940782 | F18: 1975152.5 | G18: 0.017709609
A19: 4 | B19: 8 | C19: 74641 | D19: 75974.646 | E19: 597128 | F19: 607797.17 | G19: 0.017867476
A20: 5 | B20: 8 | C20: 43337.875 | D20: 45738.592 | E20: 346703 | F20: 365908.74 | G20: 0.055395367
A21: Marketing | B21: 36 | C21: 56835.028 | D21: 58209.101 | E21: 2046061 | F21: 2095527.6 | G21: 0.024176525
A22: 1 | B22: 3 | C22: 37429.333 | D22: 37429.333 | E22: 112288 | F22: 112288 | G22: 0
A23: 2 | B23: 2 | C23: 88313 | D23: 88313 | E23: 176626 | F23: 176626 | G23: 0
A24: 3 | B24: 15 | C24: 54832.733 | D24: 55984.271 | E24: 822491 | F24: 839764.06 | G24: 0.021000911
A25: 4 | B25: 6 | C25: 88465.833 | D25: 89792.821 | E25: 530795 | F25: 538756.92 | G25: 0.015
A26: 5 | B26: 10 | C26: 40386.1 | D26: 42809.266 | E26: 403861 | F26: 428092.66 | G26: 0.06
A27: Operations | B27: 46 | C27: 51220.848 | D27: 52628.507 | E27: 2356159 | F27: 2420911.3 | G27: 0.027482144
A28: 2 | B28: 7 | C28: 74935.286 | D28: 75684.639 | E28: 524547 | F28: 529792.47 | G28: 0.01
A29: 3 | B29: 22 | C29: 46143.136 | D29: 47239.112 | E29: 1015149 | F29: 1039260.5 | G29: 0.023751656
A30: 4 | B30: 16 | C30: 45050.438 | D30: 46903.938 | E30: 720807 | F30: 750463 | G30: 0.041142775
A31: 5 | B31: 1 | C31: 95656 | D31: 101395.36 | E31: 95656 | F31: 101395.36 | G31: 0.06
A32: Sales | B32: 40 | C32: 50440.425 | D32: 52262.51 | E32: 2017617 | F32: 2090500.4 | G32: 0.036123496
A33: 1 | B33: 2 | C33: 36188.5 | D33: 36188.5 | E33: 72377 | F33: 72377 | G33: 0
A34: 2 | B34: 1 | C34: 44000 | D34: 44660 | E34: 44000 | F34: 44660 | G34: 0.015
A35: 3 | B35: 19 | C35: 40812.368 | D35: 41965.703 | E35: 775435 | F35: 797348.36 | G35: 0.028259441
A36: 4 | B36: 13 | C36: 68269.462 | D36: 71101.009 | E36: 887503 | F36: 924313.12 | G36: 0.041476051
A37: 5 | B37: 5 | C37: 47660.4 | D37: 50360.38 | E37: 238302 | F37: 251801.9 | G37: 0.056650385
A38: Grand Total | B38: 250 | C38: 55419.596 | D38: 56842.197 | E38: 13854899 | F38: 14210549 | G38: 0.025669645
A41: Pivot Summary: The pivot table provides a structured overview of salary movement following the merit cycle. This structure enables analysis of both individual salary progression (performance-based differentiation) and overall payroll impact (budget control perspective). It summarizes: -Headcount by department and performance rating -Average Gross Salary (2025 vs. 2026) -Total Payroll Before and After Merit -Budget Increase % at both department and company level Chart Summary: Salary movement before and after the merit cycle Payroll distribution across departments Relative cost impact of performance levels

Sheet Survey Matching
A1: Market Benchmarking Methodology (Mercer)
A2: Internal Title | B2: Department | C2: Job Level | D2: Job Grade | E2: Typical Scope | F2: Survey Career Level | G2: Survey Job Family | H2: People Mgmt | I2: Match Confidence
A3: IT Specialist | B3: IT | C3: Level 2 | D3: G5 | E3: Individual contributor | F3: P2 – Professional | G3: Information Technology | H3: No | I3: High
A4: Finance Specialist | B4: Finance | C4: Level 2 | D4: G5 | E4: Individual contributor | F4: P2 – Professional | G4: Finance | H4: No | I4: High
A5: Marketing Specialist | B5: Marketing | C5: Level 2 | D5: G5 | E5: Individual contributor | F5: P2 – Professional | G5: Marketing | H5: No | I5: High
A6: Sales Specialist | B6: Sales | C6: Level 2 | D6: G5 | E6: Individual contributor | F6: P2 – Professional | G6: Sales | H6: No | I6: High
A7: Operations Specialist | B7: Operations | C7: Level 2 | D7: G5 | E7: Individual contributor | F7: P2 – Professional | G7: Operations | H7: No | I7: High
A8: HR Specialist | B8: HR | C8: Level 2 | D8: G6 | E8: Experienced specialist | F8: P2 / P3 Professional | G8: Human Resources | H8: No | I8: High
A9: Financial Analyst | B9: Finance | C9: Level 2 | D9: G6 | E9: Analytical contributor | F9: P2 / P3 Professional | G9: Finance | H9: No | I9: High
A10: Senior IT Specialist | B10: IT | C10: Level 3 | D10: G7 | E10: Senior expert | F10: P3 – Senior Professional | G10: Information Technology | H10: No | I10: High
A11: Senior Finance Specialist | B11: Finance | C11: Level 3 | D11: G7 | E11: Senior expert | F11: P3 – Senior Professional | G11: Finance | H11: No | I11: High
A12: Senior HR Specialist | B12: HR | C12: Level 3 | D12: G7 | E12: Senior expert | F12: P3 – Senior Professional | G12: Human Resources | H12: No | I12: High
A13: Senior Sales Specialist | B13: Sales | C13: Level 3 | D13: G7 | E13: Senior expert | F13: P3 – Senior Professional | G13: Sales | H13: No | I13: High
... A26: CHRO | B26: HR | C26: Level 8 | D26: G10 | E26: Executive leadership | F26: Executive / C-Level | G26: Human Resources | H26: Yes | I26: High
A29: Purpose: Creating a consistent “job matching” logic so internal roles can be benchmarked against an external survey framework (Mercer-style leveling). What was done (column by column): Internal Title: The company’s internal role names (e.g., IT Specialist, HRBP, CFO). Department: Which function the role belongs to (IT, Finance, HR, etc.). Job Level: Internal career level (Level 2 / 3 / 4 / 8). Job Grade: Internal pay grade (G5–G10). Each job level maps to one grade banding logic (but Level 4 can map to G8 or G9 depending on scope). Typical Scope: Narrative scope (IC / senior expert / first-line manager / functional manager / function head / executive). Scope is used to decide survey career level. Survey Career Level: External benchmark level proxy Survey Job Family: Mercer family equivalent (IT, Finance, HR, etc.). People Mgmt (Yes/No): Whether role manages people. Used to distinguish manager levels (M1/M2). Match Confidence: High / Medium–High to signal how “clean” the match is. HRBP is “Medium–High” because it can vary widely by company scope.

Sheet Salary Band Structure
A1: SALARY BAND STRUCTURE
A2: Job Grade | B2: Job Level | C2: Roles in the pay table | D2: Band Min | E2: Band Mid (refer to mercer) | F2: Band Max | G2: Range 1 (Min→Mid) | H2: Range 2 (Mid→Max) | I2: Total Range (Min→Max)
A3: G5 | B3: Level 2 | C3: IT Specialist, Finance Specialist, Marketing Specialist, Sales Specialist, Operations Specialist | D3: 28000 | E3: 35000 | F3: 42000 | G3: =(Table4[[#This Row],[Band Mid (refer to mercer)]]-Table4[[#This Row],[Band Min]])/Table4[[#This Row],[Band Min]] -> 0.25 | H3: =(Table4[[#This Row],[Band Max]]-Table4[[#This Row],[Band Mid (refer to mercer)]])/Table4[[#This Row],[Band Mid (refer to mercer)]] -> 0.2 | I3: =(Table4[[#This Row],[Band Max]]-Table4[[#This Row],[Band Min]])/Table4[[#This Row],[Band Min]] -> 0.5
A4: G6 | B4: Level 2 | C4: HR Specialist, Financial Analyst | D4: 32000 | E4: 40000 | F4: 48000 | G4: =(Table4[[#This Row],[Band Mid (refer to mercer)]]-Table4[[#This Row],[Band Min]])/Table4[[#This Row],[Band Min]] -> 0.25 | H4: =(Table4[[#This Row],[Band Max]]-Table4[[#This Row],[Band Mid (refer to mercer)]])/Table4[[#This Row],[Band Mid (refer to mercer)]] -> 0.2 | I4: =(Table4[[#This Row],[Band Max]]-Table4[[#This Row],[Band Min]])/Table4[[#This Row],[Band Min]] -> 0.5
A5: G7 | B5: Level 3 | C5: Senior IT Specialist, Senior Finance Specialist, Senior HR Specialist, Senior Sales Specialist, HRBP | D5: 37500 | E5: 50000 | F5: 62500 | G5: =(Table4[[#This Row],[Band Mid (refer to mercer)]]-Table4[[#This Row],[Band Min]])/Table4[[#This Row],[Band Min]] -> 0.33333333 | H5: =(Table4[[#This Row],[Band Max]]-Table4[[#This Row],[Band Mid (refer to mercer)]])/Table4[[#This Row],[Band Mid (refer to mercer)]] -> 0.25 | I5: =(Table4[[#This Row],[Band Max]]-Table4[[#This Row],[Band Min]])/Table4[[#This Row],[Band Min]] -> 0.66666667
A6: G8 | B6: Level 4 | C6: Finance Manager, Sales Manager, Operations Manager, (some) HR Manager | D6: 52500 | E6: 75000 | F6: 97500 | G6: =(Table4[[#This Row],[Band Mid (refer to mercer)]]-Table4[[#This Row],[Band Min]])/Table4[[#This Row],[Band Min]] -> 0.42857143 | H6: =(Table4[[#This Row],[Band Max]]-Table4[[#This Row],[Band Mid (refer to mercer)]])/Table4[[#This Row],[Band Mid (refer to mercer)]] -> 0.3 | I6: =(Table4[[#This Row],[Band Max]]-Table4[[#This Row],[Band Min]])/Table4[[#This Row],[Band Min]] -> 0.85714286
A7: G9 | B7: Level 4 | C7: HR Manager, IT Manager, Marketing Manager, Finance Manager (higher), (some) “High” compa cases | D7: 59500 | E7: 85000 | F7: 110500 | G7: =(Table4[[#This Row],[Band Mid (refer to mercer)]]-Table4[[#This Row],[Band Min]])/Table4[[#This Row],[Band Min]] -> 0.42857143 | H7: =(Table4[[#This Row],[Band Max]]-Table4[[#This Row],[Band Mid (refer to mercer)]])/Table4[[#This Row],[Band Mid (refer to mercer)]] -> 0.3 | I7: =(Table4[[#This Row],[Band Max]]-Table4[[#This Row],[Band Min]])/Table4[[#This Row],[Band Min]] -> 0.85714286
A8: G10 | B8: Level 8 | C8: Head of Sales, Head of Marketing, Head of Operations, CFO, CHRO, Head of IT | D8: 60000 | E8: 95000 | F8: 135000 | G8: =(Table4[[#This Row],[Band Mid (refer to mercer)]]-Table4[[#This Row],[Band Min]])/Table4[[#This Row],[Band Min]] -> 0.58333333 | H8: =(Table4[[#This Row],[Band Max]]-Table4[[#This Row],[Band Mid (refer to mercer)]])/Table4[[#This Row],[Band Mid (refer to mercer)]] -> 0.42105263 | I8: =(Table4[[#This Row],[Band Max]]-Table4[[#This Row],[Band Min]])/Table4[[#This Row],[Band Min]] -> 1.25
A11: Purpose: Define the company’s internal pay bands used to calculate compa-ratio and guide increases. What was done (column by column) Job Grade: G5–G10 (matches Table 1). Job Level: The internal level tied to that grade. Roles in the pay table: Which internal titles sit in each grade. Multiple jobs can share the same grade if market level/scope is similar. Band Min / Band Mid / Band Max: The pay range values (monthly SEK). Mid = target market reference; Min/Max create a range around it. Range (Min→Max): Spread percentage to show how wide the band is. Higher grades have wider ranges due to pay variability. Output of the Table: A grade-based structure such as, G5: 30k–40k, midpoint 35k G10: much wider range, midpoint ~95k

Sheet Merit Matrix
A1: MERIT MATRIX
A2: Compa-Ratio Group | I2: Control Table
A3: Performance | B3: Very Low | C3: Below Mid | D3: Around Mid | E3: Above Mid | F3: High | I3: Total Payroll (2025) | J3: 13854899
A4: 5 | B4: 0.08 | C4: 0.07 | D4: 0.06 | E4: 0.04 | F4: 0.02 | I4: Proposed Merit Increase % | J4: 0.03
A5: 4 | B5: 0.06 | C5: 0.05 | D5: 0.04 | E5: 0.03 | F5: 0.015 | I5: Desired Budget % | J5: 0.03
A6: 3 | B6: 0.04 | C6: 0.03 | D6: 0.025 | E6: 0.02 | F6: 0.01 | I6: Desired Budget POT | J6: =J3*J5 -> 415646.97
A7: 2 | B7: 0.02 | C7: 0.015 | D7: 0.01 | E7: 0.005 | F7: 0 | I7: TOTAL MERIT SPEND % | J7: 0.0227
A8: 1 | B8: 0 | C8: 0 | D8: 0 | E8: 0 | F8: 0 | I8: TOTAL MERIT SPEND | J8: 355650
I9: AVERAGE INCREASE PER EMPLOYEE | J9: =J8/250 -> 1422.6
I10: Remaining Budget Capacity | J10: =J6-J8 -> 59996.97
A11: Purpose: This merit matrix was fictively designed for modeling purposes, but it follows standard compensation and total rewards practices. The purpose of combining performance and compa-ratio groups is to balance: -Pay-for-performance philosophy -Internal equity and market alignment Dimensions: Performance Rating (vertical axis) – differentiates reward based on individual contribution. Compa-Ratio Group (horizontal axis) – adjusts increases based on an employee’s position within the pay range. Performance Differentiation Higher performance ratings receive higher salary increases. For example: Performance 5 receives the highest increase range (2%–8%). Performance 1 receives 0%, regardless of compa-ratio. This ensures meaningful differentiation between performance levels. Compa-Ratio Adjustment Salary increases decrease as compa-ratio increases. Employees in the “Very Low” compa group receive higher increases to accelerate movement toward midpoint. Employees in the “High” compa group receive lower increases because they are already positioned near or above the pay band midpoint. This supports internal equity and prevents excessive range penetration. Percentage Calibration: The percentage values were not taken from a specific company but were calibrated to reflect common market practice. Typical annual merit budgets: ~2%–4% of payroll High performers: often 5%–8% Low performers: 0%–1% High compa employees: lower increases The matrix was structured so that, when applied to the full employee dataset, the overall company payroll increase results in approximately 2.5–3% total budget impact, which aligns with realistic merit cycle scenarios.
I13: Merit increases are calculated based on 2025 total payroll (13,854,899 SEK) Proposed merit budget target is 3% of total payroll (fictive). For "total merit spend" values, check the pivot table All eligible employees are included (N = 250) **POT = Payroll on Target

Sheet STI Notes
B3: Job Level | C3: Target STI % | E3: Performance Rating | F3: Multiplier/LTI
B4: Junior / Entry Specialist | C4: 0.1 | E4: 5 (Excellent) | F4: 1.5
B5: Mid / Senior Specialist | C5: 0.15 | E5: 4 (Good) | F5: 1.2
B6: Manager | C6: 0.2 | E6: 3 (Meets Expectation) | F6: 1
B7: Executive | C7: 0.25 | E7: 2 (Below Expectation) | F7: 0.5
E8: 1 (Poor) | F8: 0
E10: Performance Multiplier is applied to Target STI/LTI to adjust payout based on individual performance rating
E11: Note: Merit matrix is not used here as it only affects base salary adjustments, not incentive payouts.

Sheet Notes for Employee Dataset
A1: Summary of Employee Dataset
A2: STAGE 1 A) Employee + job info (input columns) Employee ID / Name Department / Title Recruitment Date Performance Manager Unit / Location Country Job Level Job Grade Assumption: Job grade is already decided via job architecture (Table 1). | B2: STAGE 2 B) Current salary + bring pay band values Monthly Gross Salary (2025): current base salary (monthly SEK) Min / Mid / Max: pulled from Table 2 using Job Grade Assumption: one band per grade for all employees. C) Compa-ratio calculations Compa_Ratio (GrossSalary/Mid) Compa-Ratio Group: bucket assignment from compa-ratio. Compa Group Thresholds: Very Low: <0.85 Below Mid: 0.85–0.95 Around Mid: 0.95–1.05 Above Mid: 1.05–1.15 High: ≥1.15 Assumption: Thresholds are fixed for demo and apply equally across grades. D) Performance input Performance: rating 1–5 Assumption: final rating (no calibration step shown). | C2: STAGE 3 E) Merit increase lookup (uses Table 3) Salary increase %: 2D lookup (Performance row, Compa group column) → % Salary increase Amount: Monthly Gross Salary × Salary increase % New Gross Salary: Monthly Gross Salary + Salary increase Amount Assumption: No promotions/adjustments outside merit matrix. | D2: STAGE 4 F) STI Determine Target STI (% of salary) Multiply by Performance Multiplier to get Final STI: Final STI = Target STI × Performance Multiplier | E2: STAGE 5 G) Deductions & net pay Tax %: employee tax rate (input) Benefit Plan (A/B/C): input that drives health premium Tax Amount: New Gross Salary × Tax % Pension: New Gross Salary × 5%. Flat 5% for all. Health Premium (A/B/C): A = 500 B = 800 C = 1200 Assumption: flat cost (not %). Total Deductions: Tax + Pension + Health Premium Net Pay: New Gross Salary – Total Deductions
